{
  "$schema": "https://biomejs.dev/schemas/1.9.0/schema.json",
  "organizeImports": {
    "enabled": true
  },
  "formatter": {
    "enabled": true,
    "indentStyle": "space",
    "indentWidth": 2,
    "lineWidth": 100
  },
  "linter": {
    "enabled": true,
    "rules": {
      "recommended": true,
      "complexity": {
        "noExcessiveCognitiveComplexity": "warn"
      },
      "style": {
        "useConst": "error",
        "noNonNullAssertion": "warn"
      },
      "suspicious": {
        "noExplicitAny": "warn"
      }
    }
  },
  "javascript": {
    "formatter": {
      "quoteStyle": "single",
      "trailingCommas": "all",
      "semicolons": "asNeeded"
    }
  }
}
